odoo8_addon_product_attribute_priority-8.0.1.0.0.99.dev6-py2.7-nspkg.pth
odoo8_addon_product_attribute_priority-8.0.1.0.0.99.dev6.dist-info/DESCRIPTION.rst
odoo8_addon_product_attribute_priority-8.0.1.0.0.99.dev6.dist-info/METADATA
odoo8_addon_product_attribute_priority-8.0.1.0.0.99.dev6.dist-info/RECORD
odoo8_addon_product_attribute_priority-8.0.1.0.0.99.dev6.dist-info/WHEEL
odoo8_addon_product_attribute_priority-8.0.1.0.0.99.dev6.dist-info/metadata.json
odoo8_addon_product_attribute_priority-8.0.1.0.0.99.dev6.dist-info/namespace_packages.txt
odoo8_addon_product_attribute_priority-8.0.1.0.0.99.dev6.dist-info/top_level.txt
odoo_addons/product_attribute_priority/README.rst
odoo_addons/product_attribute_priority/__init__.py
odoo_addons/product_attribute_priority/__openerp__.py
odoo_addons/product_attribute_priority/i18n/de.po
odoo_addons/product_attribute_priority/i18n/es.po
odoo_addons/product_attribute_priority/i18n/fr.po
odoo_addons/product_attribute_priority/i18n/product_attribute_priority.pot
odoo_addons/product_attribute_priority/i18n/sl.po
odoo_addons/product_attribute_priority/models/__init__.py
odoo_addons/product_attribute_priority/models/product.py
odoo_addons/product_attribute_priority/static/description/icon.png
odoo_addons/product_attribute_priority/views/product_view.xml
